phonexia_enhanced_speech_to_text_built_on_whisper_client.py
phonexia_enhanced_speech_to_text_built_on_whisper_client-2.1.0.dist-info/METADATA
phonexia_enhanced_speech_to_text_built_on_whisper_client-2.1.0.dist-info/WHEEL
phonexia_enhanced_speech_to_text_built_on_whisper_client-2.1.0.dist-info/entry_points.txt
phonexia_enhanced_speech_to_text_built_on_whisper_client-2.1.0.dist-info/top_level.txt
phonexia_enhanced_speech_to_text_built_on_whisper_client-2.1.0.dist-info/RECORD
